Metadata-Version: 2.1
Name: odoo12-addon-purchase_sale_inter_company
Version: 12.0.1.3.2
Summary: Intercompany PO/SO rules
Home-page: https://github.com/OCA/multi-company
Author: Odoo SA, Akretion, Tecnativa, Odoo Community Association (OCA)
Author-email: support@odoo-community.org
License: AGPL-3
Classifier: Programming Language :: Python
Classifier: Framework :: Odoo
Classifier: Framework :: Odoo :: 12.0
Classifier: License :: OSI Approved :: GNU Affero General Public License v3
Requires-Python: >=3.5
Requires-Dist: odoo12-addon-account-invoice-inter-company
Requires-Dist: odoo<12.1dev,>=12.0a
